mofi/__init__.py
mofi/schemas.py
mofi/server.py
mofi-0.1.1.dist-info/LICENSE
mofi-0.1.1.dist-info/METADATA
mofi-0.1.1.dist-info/WHEEL
mofi-0.1.1.dist-info/RECORD
