Metadata-Version: 2.1
Name: mofi
Version: 0.1.1
Summary: Webhook wrapper for ko-fi
License: MIT
Author: Jedddy
Author-email: jedbalita25@gmail.com
Requires-Python: >=3.9,<4.0
Classifier: License :: OSI Approved :: MIT License
Classifier: Programming Language :: Python :: 3
Classifier: Programming Language :: Python :: 3.9
Classifier: Programming Language :: Python :: 3.10
Classifier: Programming Language :: Python :: 3.11
Classifier: Programming Language :: Python :: 3.12
Requires-Dist: fastapi (>=0.109.0,<0.110.0)
Requires-Dist: python-multipart (>=0.0.6,<0.0.7)
Requires-Dist: uvicorn (>=0.25.0,<0.26.0)
